{"trial_id": "0024", "hyperparameters": {"space": [{"class_name": "Choice", "config": {"name": "lstm_units", "default": 16, "conditions": [], "values": [16, 32, 64, 128, 256], "ordered": true}}, {"class_name": "Choice", "config": {"name": "lr", "default": 0.01, "conditions": [], "values": [0.01, 0.001, 0.0001], "ordered": true}}, {"class_name": "Choice", "config": {"name": "optim", "default": "Adam", "conditions": [], "values": ["Adam", "SGD", "RMSProp"], "ordered": false}}], "values": {"lstm_units": 128, "lr": 0.01, "optim": "Adam", "tuner/epochs": 10, "tuner/initial_epoch": 4, "tuner/bracket": 1, "tuner/round": 1, "tuner/trial_id": "0022"}}, "metrics": {"metrics": {"loss": {"direction": "min", "observations": [{"value": [0.013998235575854778], "step": 4}]}, "accuracy": {"direction": "max", "observations": [{"value": [0.9548836946487427], "step": 4}]}, "val_loss": {"direction": "min", "observations": [{"value": [0.04324933886528015], "step": 4}]}, "val_accuracy": {"direction": "max", "observations": [{"value": [0.8754479289054871], "step": 4}]}}}, "score": 0.8754479289054871, "best_step": 4, "status": "COMPLETED"}